autogluon.core-1.4.0-py3.9-nspkg.pth
autogluon/core/__init__.py
autogluon/core/_setup_utils.py
autogluon/core/constants.py
autogluon/core/problem_type.py
autogluon/core/version.py
autogluon/core/augmentation/__init__.py
autogluon/core/augmentation/distill_utils.py
autogluon/core/calibrate/__init__.py
autogluon/core/calibrate/_decision_threshold.py
autogluon/core/calibrate/conformity_score.py
autogluon/core/calibrate/temperature_scaling.py
autogluon/core/callbacks/__init__.py
autogluon/core/callbacks/_abstract_callback.py
autogluon/core/callbacks/_early_stopping_callback.py
autogluon/core/callbacks/_early_stopping_ensemble_callback.py
autogluon/core/callbacks/_example_callback.py
autogluon/core/data/__init__.py
autogluon/core/data/cleaner.py
autogluon/core/data/label_cleaner.py
autogluon/core/hpo/__init__.py
autogluon/core/hpo/constants.py
autogluon/core/hpo/exceptions.py
autogluon/core/hpo/executors.py
autogluon/core/hpo/ray_hpo.py
autogluon/core/hpo/ray_tune_constants.py
autogluon/core/hpo/ray_tune_scheduler.py
autogluon/core/hpo/ray_tune_scheduler_factory.py
autogluon/core/hpo/ray_tune_searcher_factory.py
autogluon/core/hpo/space_converter.py
autogluon/core/learner/__init__.py
autogluon/core/learner/abstract_learner.py
autogluon/core/learning_curves/plot_curves.py
autogluon/core/metrics/__init__.py
autogluon/core/metrics/classification_metrics.py
autogluon/core/metrics/quantile_metrics.py
autogluon/core/metrics/score_func.py
autogluon/core/metrics/softclass_metrics.py
autogluon/core/models/__init__.py
autogluon/core/models/_utils.py
autogluon/core/models/abstract/__init__.py
autogluon/core/models/abstract/_tags.py
autogluon/core/models/abstract/abstract_model.py
autogluon/core/models/abstract/abstract_nn_model.py
autogluon/core/models/abstract/model_trial.py
autogluon/core/models/dummy/__init__.py
autogluon/core/models/dummy/_dummy_quantile_regressor.py
autogluon/core/models/dummy/dummy_model.py
autogluon/core/models/ensemble/__init__.py
autogluon.core-1.4.0.dist-info/LICENSE
autogluon.core-1.4.0.dist-info/METADATA
autogluon.core-1.4.0.dist-info/NOTICE
autogluon.core-1.4.0.dist-info/WHEEL
autogluon.core-1.4.0.dist-info/namespace_packages.txt
autogluon.core-1.4.0.dist-info/top_level.txt
autogluon.core-1.4.0.dist-info/zip-safe
autogluon.core-1.4.0.dist-info/RECORD
