Metadata-Version: 2.1
Name: autogluon.core
Version: 1.4.0
Summary: Fast and Accurate ML in 3 Lines of Code
Home-page: https://github.com/autogluon/autogluon
Author: AutoGluon Community
License: Apache-2.0
Project-URL: Documentation, https://auto.gluon.ai
Project-URL: Bug Reports, https://github.com/autogluon/autogluon/issues
Project-URL: Source, https://github.com/autogluon/autogluon/
Project-URL: Contribute!, https://github.com/autogluon/autogluon/blob/master/CONTRIBUTING.md
Platform: UNKNOWN
Classifier: Development Status :: 5 - Production/Stable
Classifier: Intended Audience :: Education
Classifier: Intended Audience :: Developers
Classifier: Intended Audience :: Science/Research
Classifier: Intended Audience :: Customer Service
Classifier: Intended Audience :: Financial and Insurance Industry
Classifier: Intended Audience :: Healthcare Industry
Classifier: Intended Audience :: Telecommunications Industry
Classifier: License :: OSI Approved :: Apache Software License
Classifier: Operating System :: MacOS
Classifier: Operating System :: Microsoft :: Windows
Classifier: Operating System :: POSIX
Classifier: Operating System :: Unix
Classifier: Programming Language :: Python :: 3
Classifier: Programming Language :: Python :: 3.9
Classifier: Programming Language :: Python :: 3.10
Classifier: Programming Language :: Python :: 3.11
Classifier: Programming Language :: Python :: 3.12
Classifier: Topic :: Software Development
Classifier: Topic :: Scientific/Engineering :: Artificial Intelligence
Classifier: Topic :: Scientific/Engineering :: Information Analysis
Classifier: Topic :: Scientific/Engineering :: Image Recognition
Requires-Python: >=3.9, <3.13
License-File: ../LICENSE
License-File: ../NOTICE
Requires-Dist: numpy<2.4.0,>=1.25.0
Requires-Dist: scipy<1.17,>=1.5.4
Requires-Dist: scikit-learn<1.8.0,>=1.4.0
Requires-Dist: networkx<4,>=3.0
Requires-Dist: pandas<2.4.0,>=2.0.0
Requires-Dist: tqdm<5,>=4.38
Requires-Dist: requests
Requires-Dist: matplotlib<3.11,>=3.7.0
Requires-Dist: boto3<2,>=1.10
Requires-Dist: autogluon.common==1.4.0
Provides-Extra: all
Requires-Dist: hyperopt<0.2.8,>=0.2.7; extra == "all"
Requires-Dist: pyarrow>=15.0.0; extra == "all"
Requires-Dist: ray[default,tune]<2.45,>=2.10.0; extra == "all"
Requires-Dist: ray[default]<2.45,>=2.10.0; extra == "all"
Provides-Extra: ray
Requires-Dist: ray[default]<2.45,>=2.10.0; extra == "ray"
Provides-Extra: raytune
Requires-Dist: pyarrow>=15.0.0; extra == "raytune"
Requires-Dist: ray[default,tune]<2.45,>=2.10.0; extra == "raytune"
Requires-Dist: hyperopt<0.2.8,>=0.2.7; extra == "raytune"
Provides-Extra: tests
Requires-Dist: types-setuptools; extra == "tests"
Requires-Dist: flake8; extra == "tests"
Requires-Dist: types-requests; extra == "tests"
Requires-Dist: pytest; extra == "tests"
Requires-Dist: pytest-mypy; extra == "tests"
